trevis/__init__.py
trevis-0.0.1.dist-info/METADATA
trevis-0.0.1.dist-info/WHEEL
trevis-0.0.1.dist-info/licenses/LICENSE
trevis-0.0.1.dist-info/RECORD
