Metadata-Version: 2.3
Name: trevis
Version: 0.0.1
Summary: trevis
Project-URL: Bug Tracker, https://github.com/cabralpinto/trevis/issues
Author-email: João Cabral Pinto <jmcabralpinto@gmail.com>
License-File: LICENSE
Classifier: License :: OSI Approved :: MIT License
Classifier: Operating System :: OS Independent
Classifier: Programming Language :: Python :: 3
Requires-Python: >=3.6
